minepkg/__init__.py
minepkg/cmdline.py
minepkg/installer.py
minepkg/makerepo.py
minepkg/repository.py
minepkg-0.2.dist-info/METADATA
minepkg-0.2.dist-info/WHEEL
minepkg-0.2.dist-info/entry_points.txt
minepkg-0.2.dist-info/top_level.txt
minepkg-0.2.dist-info/RECORD
