Metadata-Version: 2.1
Name: minepkg
Version: 0.2
Summary: A package manager for minetest mods
Home-page: https://gitlab.com/MartijnBraam/minepkg
Author: Martijn Braam
Author-email: martijn@brixit.nl
License: MIT
Keywords: minetest
Platform: UNKNOWN
Classifier: Development Status :: 3 - Alpha
Classifier: License :: OSI Approved :: MIT License
Classifier: Programming Language :: Python :: 3
Classifier: Programming Language :: Python :: 3.4
Classifier: Programming Language :: Python :: 3.5
Classifier: Programming Language :: Python :: 3.6
Requires-Python: >=3.4
Requires-Dist: tqdm
Requires-Dist: pyxdg
Requires-Dist: requests
